reproserver/__init__.py
reproserver/build.py
reproserver/database.py
reproserver/main.py
reproserver/objectstore.py
reproserver/repositories/__init__.py
reproserver/repositories/base.py
reproserver/repositories/figshare.py
reproserver/repositories/osf.py
reproserver/repositories/zenodo.py
reproserver/run.py
reproserver/shortid.py
reproserver/static/css/bootstrap-theme.min.css
reproserver/static/css/bootstrap.min.css
reproserver/static/css/custom.css
reproserver/static/fonts/glyphicons-halflings-regular.eot
reproserver/static/fonts/glyphicons-halflings-regular.svg
reproserver/static/fonts/glyphicons-halflings-regular.ttf
reproserver/static/fonts/glyphicons-halflings-regular.woff
reproserver/static/fonts/glyphicons-halflings-regular.woff2
reproserver/static/js/bootstrap.min.js
reproserver/static/js/jquery.min.js
reproserver/templates/about.html
reproserver/templates/base.html
reproserver/templates/data.html
reproserver/templates/index.html
reproserver/templates/provider_notfound.html
reproserver/templates/results.html
reproserver/templates/results_notfound.html
reproserver/templates/setup.html
reproserver/templates/setup_notfound.html
reproserver/utils.py
reproserver/web/__init__.py
reproserver/web/base.py
reproserver/web/views.py
reproserver-0.7.dist-info/entry_points.txt
reproserver-0.7.dist-info/LICENSE.txt
reproserver-0.7.dist-info/WHEEL
reproserver-0.7.dist-info/METADATA
reproserver-0.7.dist-info/RECORD
